jsonpath/__init__.py
jsonpath_python-1.0.5.dist-info/LICENSE
jsonpath_python-1.0.5.dist-info/METADATA
jsonpath_python-1.0.5.dist-info/WHEEL
jsonpath_python-1.0.5.dist-info/top_level.txt
jsonpath_python-1.0.5.dist-info/RECORD
