Metadata-Version: 2.1
Name: jsonpath-python
Version: 1.0.5
Summary: A more powerful JSONPath implementation in modern python
Home-page: https://github.com/zhangxianbing/jsonpath-python
Author: zhangxianbing
License: UNKNOWN
Platform: UNKNOWN
Classifier: Programming Language :: Python :: 3.6
Classifier: License :: OSI Approved :: MIT License
Classifier: Operating System :: OS Independent
Requires-Python: >=3.6
